setup.py
src/mqueue/__init__.py
src/mqueue/db.py
src/mqueue/decorators.py
src/mqueue/scheduler.py
src/mqueue/schedules.py
src/mqueue/util.py
src/mqueue/worker.py
src/mqueue.egg-info/PKG-INFO
src/mqueue.egg-info/SOURCES.txt
src/mqueue.egg-info/dependency_links.txt
src/mqueue.egg-info/requires.txt
src/mqueue.egg-info/top_level.txt
test/testutil.py