Metadata-Version: 1.1
Name: mqueue
Version: 0.4.4
Summary: Simple queue based on mysql.
Home-page: https://package-insights.appspot.com/packages/mqueue
Author: Mengchen LEE
Author-email: CooledCoffee@gmail.com
License: UNKNOWN
Platform: UNKNOWN
Classifier: Development Status :: 4 - Beta
Classifier: Intended Audience :: Developers
Classifier: Operating System :: OS Independent
Classifier: Programming Language :: Python
Classifier: Programming Language :: Python :: 2
Classifier: Topic :: Software Development :: Libraries
